tk1/__init__.py
tk1/topsis.py
TOPSIS_Karan_101853003-1.0.0.dist-info/LICENSE
TOPSIS_Karan_101853003-1.0.0.dist-info/METADATA
TOPSIS_Karan_101853003-1.0.0.dist-info/WHEEL
TOPSIS_Karan_101853003-1.0.0.dist-info/top_level.txt
TOPSIS_Karan_101853003-1.0.0.dist-info/RECORD
