Metadata-Version: 2.1
Name: TOPSIS-Karan-101853003
Version: 1.0.0
Summary: Topsis score calculator
Home-page: https://github.com/KARANQUERNMADAVIDE/TOPSIS-Karan-101853003
Author: Karan Madan
Author-email: kmadan_be18@thapar.edu
License: MIT
Keywords: topsis,thapar,rank,topsis score
Platform: UNKNOWN
Classifier: Development Status :: 5 - Production/Stable
Classifier: Intended Audience :: Developers
Classifier: Topic :: Software Development :: Build Tools
Classifier: License :: OSI Approved :: MIT License
Classifier: Programming Language :: Python :: 3.6
Classifier: Programming Language :: Python :: 3.7
Classifier: Programming Language :: Python :: 3.8
Requires-Dist: pandas
